coinor.gimpy-2.1.1-py2.7-nspkg.pth
coinor/gimpy/__init__.py
coinor/gimpy/global_constants.py
coinor/gimpy/graph.py
coinor/gimpy/tree.py
coinor/gimpy/examples/BB.py
coinor/gimpy/examples/SAT.py
coinor/gimpy/examples/__init__.py
coinor/gimpy/examples/expression_tree.py
coinor/gimpy/examples/forestry.py
coinor/gimpy/examples/maxflow.py
coinor/gimpy/examples/milp1.py
coinor/gimpy/examples/milp2.py
coinor/gimpy/examples/milp3.py
coinor/gimpy/examples/mincostflow.py
coinor/gimpy/examples/postordereval.py
coinor/gimpy/examples/prerequisites.py
coinor/gimpy/examples/search.py
coinor/gimpy/examples/simplex_test.py
coinor/gimpy/examples/simplex_visualization_test.py
coinor.gimpy-2.1.1.dist-info/DESCRIPTION.rst
coinor.gimpy-2.1.1.dist-info/METADATA
coinor.gimpy-2.1.1.dist-info/RECORD
coinor.gimpy-2.1.1.dist-info/WHEEL
coinor.gimpy-2.1.1.dist-info/metadata.json
coinor.gimpy-2.1.1.dist-info/namespace_packages.txt
coinor.gimpy-2.1.1.dist-info/top_level.txt
