Metadata-Version: 2.0
Name: coinor.gimpy
Version: 2.1.1
Summary: Graph Methods in Python
Home-page: https://github.com/coin-or/GiMPy/
Author: Aykut Bulut, Ted Ralphs
Author-email: ted@lehigh.edu
License: Eclipse Public License
Platform: UNKNOWN
Requires-Dist: coinor.blimpy (>=2.0.0)
